{"game":
[{"start":{}},
{"settings":{"splurges":true,"options":true}},
{"map":"circle.json"},
{"punter":0,"team":"DNIWE :: a"},
{"punter":1,"team":"yarunee"},
{"punter":2,"team":"MindSweeper"},
{"punter":3,"team":"TFS_is_shit"},
{"gameplay":"start"},
{"timeout":{"punter":0}},
{"pass":{"punter":0}},
{"claim":{"punter":1,"source":12,"target":26}},
{"claim":{"punter":2,"source":24,"target":26}},
{"claim":{"punter":3,"source":24,"target":25}},
{"timeout":{"punter":0}},
{"pass":{"punter":0}},
{"claim":{"punter":1,"source":26,"target":18}},
{"claim":{"punter":2,"source":6,"target":26}},
{"claim":{"punter":3,"source":6,"target":7}},
{"timeout":{"punter":0}},
{"pass":{"punter":0}},
{"claim":{"punter":1,"source":26,"target":2}},
{"claim":{"punter":2,"source":18,"target":20}},
{"claim":{"punter":3,"source":6,"target":4}},
{"timeout":{"punter":0}},
{"pass":{"punter":0}},
{"claim":{"punter":1,"source":2,"target":3}},
{"claim":{"punter":2,"source":26,"target":20}},
{"claim":{"punter":3,"source":12,"target":13}},
{"timeout":{"punter":0}},
{"pass":{"punter":0}},
{"claim":{"punter":1,"source":3,"target":1}},
{"claim":{"punter":2,"source":12,"target":14}},
{"claim":{"punter":3,"source":18,"target":17}},
{"timeout":{"punter":0}},
{"pass":{"punter":0}},
{"claim":{"punter":1,"source":1,"target":2}},
{"claim":{"punter":2,"source":26,"target":14}},
{"claim":{"punter":3,"source":12,"target":11}},
{"timeout":{"punter":0}},
{"pass":{"punter":0}},
{"claim":{"punter":1,"source":1,"target":25}},
{"claim":{"punter":2,"source":14,"target":15}},
{"claim":{"punter":3,"source":11,"target":13}},
{"timeout":{"punter":0}},
{"pass":{"punter":0}},
{"claim":{"punter":1,"source":25,"target":23}},
{"claim":{"punter":2,"source":20,"target":21}},
{"claim":{"punter":3,"source":6,"target":5}},
{"timeout":{"punter":0}},
{"pass":{"punter":0}},
{"claim":{"punter":1,"source":23,"target":21}},
{"claim":{"punter":2,"source":16,"target":18}},
{"claim":{"punter":3,"source":13,"target":14}},
{"timeout":{"punter":0}},
{"zombie":{"punter":0}},
{"claim":{"punter":1,"source":21,"target":19}},
{"claim":{"punter":2,"source":13,"target":15}},
{"claim":{"punter":3,"source":5,"target":3}},
{"pass":{"punter":0}},
{"claim":{"punter":1,"source":19,"target":17}},
{"claim":{"punter":2,"source":10,"target":12}},
{"claim":{"punter":3,"source":24,"target":0}},
{"pass":{"punter":0}},
{"claim":{"punter":1,"source":17,"target":15}},
{"claim":{"punter":2,"source":9,"target":10}},
{"claim":{"punter":3,"source":11,"target":9}},
{"pass":{"punter":0}},
{"claim":{"punter":1,"source":15,"target":16}},
{"claim":{"punter":2,"source":6,"target":8}},
{"claim":{"punter":3,"source":18,"target":19}},
{"pass":{"punter":0}},
{"claim":{"punter":1,"source":16,"target":14}},
{"claim":{"punter":2,"source":7,"target":8}},
{"claim":{"punter":3,"source":19,"target":20}},
{"pass":{"punter":0}},
{"claim":{"punter":1,"source":16,"target":26}},
{"claim":{"punter":2,"source":23,"target":24}},
{"claim":{"punter":3,"source":4,"target":5}},
{"pass":{"punter":0}},
{"claim":{"punter":1,"source":16,"target":17}},
{"claim":{"punter":2,"source":22,"target":23}},
{"claim":{"punter":3,"source":5,"target":7}},
{"pass":{"punter":0}},
{"gameplay":"stop"},
{"pass":{"punter":0}},
{"scores":[{"punter":0,"score":0,"team":"DNIWE :: a"},{"punter":1,"score":141,"team":"yarunee"},{"punter":2,"score":292,"team":"MindSweeper"},{"punter":3,"score":19,"team":"TFS_is_shit"}]},
{"statuses":[{"punter":0,"active":false},{"punter":1,"active":true,"credit":0,"options":4},{"punter":2,"active":true,"credit":0,"options":4},{"punter":3,"active":true,"credit":0,"options":4}]},
 {"stop":{}}]}
